pydiary/__init__.py
pydiary/__main__.py
pydiary-1.1.0.dist-info/LICENSE
pydiary-1.1.0.dist-info/METADATA
pydiary-1.1.0.dist-info/WHEEL
pydiary-1.1.0.dist-info/top_level.txt
pydiary-1.1.0.dist-info/RECORD
