Metadata-Version: 2.1
Name: pydiary
Version: 1.1.0
Summary: MatLab style commands logger for the Python interpreter
Home-page: https://github.com/nathanlepori/pydiary
Author: Nathan Lepori
Author-email: nathan.lepori@hotmail.com
License: MIT
Platform: UNKNOWN
Classifier: Programming Language :: Python :: 3
Classifier: License :: OSI Approved :: MIT License
Classifier: Operating System :: OS Independent
Classifier: Development Status :: 5 - Production/Stable
